alu_latch.sv
//-----------------------------------------------------------------------------
//
// Title       : ALU Latch
// Author      : vinod sake <vinosake@pdx.edu>
// Company     : Student
//
//-----------------------------------------------------------------------------
//
// File        : alu_latch.sv
// Generated   : 20 Nov 2016
// Last Updated: 
//-----------------------------------------------------------------------------
//
// Description : Takes the ALU output result and put in data bus 
//		 	
//-----------------------------------------------------------------------------

module alu_latch(
	input clock,			// System clock
	input reset,			// Syetem reset
	input store_high,		// Load top 8 bits on data bus
	input store_low,		// Load low 8 bits on data bus
	input grab,			// latch ALU result 
	input [15:0]alu_result,		// alu result from ALU module
	input [2:0]flags_in,		// flags result from ALU module
	output logic[7:0]data_out,	// 8 bits data is loaded into data bus
	output logic[2:0]flags_out	// 3 bits flag result
);
logic [15:0]alu_value;

always@(posedge clock) begin
	if(reset == 1'b0) begin		
		alu_value = 16'd0;
		flags_out = 3'd0;
	end
	else if(grab == 1'b1) begin		// latch alu result when grab signal is high
		alu_value <= alu_result;	 
		flags_out <= flags_in;		
	end
end

always_comb begin
	if(store_high == 1'b1) begin		// Load top 8 bits of alu result on data bus
		data_out <= alu_value[15:8];
	end
	else if(store_low == 1'b1) begin	// Load low 8 bits of alu result on data bus
		data_out <= alu_value[7:0];
	end
	else begin
		data_out <= 8'hzz;		// Else maintain high impedance on data bus
	end
end
endmodule

alu_latch_tb.sv
//-----------------------------------------------------------------------------
//
// Title       : ALU Latch Testbench
// Author      : vinod sake <vinosake@pdx.edu>
// Company     : Student
//
//-----------------------------------------------------------------------------
//
// File        : alu_latch_tb.sv
// Generated   : 18 Dec 2016
// Last Updated: 
//-----------------------------------------------------------------------------
//
// Description : Perform testing on latch operations 
//		  	
//-----------------------------------------------------------------------------
`include "alu_latch.sv"

module alu_latch_tb();
	logic clock = 1'b0;		// System clock
	logic reset = 1'b1;		// Syetem reset
	logic store_high;		// Load top 8 bits on data bus
	logic store_low;		// Load low 8 bits on data bus
	logic grab;			// latch ALU result 
	logic [15:0]alu_result;		// alu result from ALU module
	logic [2:0]flags_in;		// flags result from ALU module
	logic [7:0]data_out;		// 8 bits data is loaded into data bus
	logic [2:0]flags_out;		// 3 bits flag result

//clock
initial clock = 1'b0;
always #50 clock = !clock; // 100 time ticks per cycle = 10 MHz clock

alu_latch alu_latch_dut(
	.clock(clock),
	.reset(reset),
	.store_high(store_high),
	.store_low(store_low),
	.grab(grab),
	.alu_result(alu_result),
	.flags_in(flags_in),
	.data_out(data_out),
	.flags_out(flags_out)
);

initial begin
	// Reset
	@(negedge clock) begin
		reset = 1'b0;
	end
	checkCount(8'hzz,3'd0, `__LINE__);

	@(negedge clock) begin
		reset = 1'b1;
	end
	checkCount(8'hzz,3'd0, `__LINE__);

	@(negedge clock) begin
		grab = 1'b1;				// alu reult should be grabed and stored in internal register
		alu_result = 16'hfeef;
		flags_in = 3'b101;
	end
	checkCount(8'hzz,3'b101, `__LINE__);

	@(negedge clock) begin
		grab = 1'b0;
		alu_result = 16'heffe;
		flags_in = 3'b111;
	end
	checkCount(8'hzz,3'b101, `__LINE__);

	@(negedge clock) begin
		store_high = 1'b1;			// data out should have high 8 bits of internal register
	end
	checkCount(8'hfe,3'b101, `__LINE__);
	
	@(negedge clock) begin
		store_high = 1'b0;
	end
	checkCount(8'hzz,3'b101, `__LINE__);

	@(negedge clock) begin
		store_low = 1'b1;			// data out should have low 8 bits of internal register
	end
	checkCount(8'hef,3'b101, `__LINE__);

	@(negedge clock) begin
		store_low = 1'b0;
	end
	checkCount(8'hzz,3'b101, `__LINE__);
	
	@(negedge clock) begin				// As store_high has higher precedence, data out should have high 8 bits of internal register 
		store_high = 1'b1;
		store_low = 1'b1;
	end
	checkCount(8'hfe,3'b101, `__LINE__);

	$finish;
end

// Waveform log file and monitoring
initial begin
	$dumpfile("alu_latch.vcd");
	$dumpvars();
	//$monitor("time: %d, data out: %d, flags out: %d ", $time, data_out, flags_out);
end

task checkCount(input [7:0]data_expected, input [2:0]flags_expected, input integer lineNum);
begin
	@(posedge clock) #5 begin
		if(data_out === data_expected) begin
			$display("%3d - Test passed! for Data Out", lineNum);
		end
		else begin
			$display("%3d - Test failed! for Data Out, expected %d, got %d", lineNum, data_expected, data_out);
		end
		if(flags_out == flags_expected) begin
			$display("%3d - Test passed! for Flags Out", lineNum);
		end
		else begin
			$display("%3d - Test failed! for Flags Out, expected %d, got %d", lineNum, flags_expected, flags_out);
		end
	end
end
endtask

endmodule

program_counter.vcd
$date
	Sun Dec 18 21:52:11 2016
$end
$version
	ModelSim Version 10.4a
$end
$timescale
	1ns
$end

$scope module alu_latch_tb $end
$var reg 1 ! clock $end
$var reg 1 " reset $end
$var reg 1 # store_high $end
$var reg 1 $ store_low $end
$var reg 1 % grab $end
$var reg 16 & alu_result [15:0] $end
$var reg 3 ' flags_in [2:0] $end
$var reg 8 ( data_out [7:0] $end
$var reg 3 ) flags_out [2:0] $end

$scope task checkCount $end
$var reg 8 * data_expected [7:0] $end
$var reg 3 + flags_expected [2:0] $end
$var integer 32 , lineNum $end
$upscope $end

$scope module alu_latch_dut $end
$var wire 1 - clock $end
$var wire 1 . reset $end
$var wire 1 / store_high $end
$var wire 1 0 store_low $end
$var wire 1 1 grab $end
$var wire 1 2 alu_result [15] $end
$var wire 1 3 alu_result [14] $end
$var wire 1 4 alu_result [13] $end
$var wire 1 5 alu_result [12] $end
$var wire 1 6 alu_result [11] $end
$var wire 1 7 alu_result [10] $end
$var wire 1 8 alu_result [9] $end
$var wire 1 9 alu_result [8] $end
$var wire 1 : alu_result [7] $end
$var wire 1 ; alu_result [6] $end
$var wire 1 < alu_result [5] $end
$var wire 1 = alu_result [4] $end
$var wire 1 > alu_result [3] $end
$var wire 1 ? alu_result [2] $end
$var wire 1 @ alu_result [1] $end
$var wire 1 A alu_result [0] $end
$var wire 1 B flags_in [2] $end
$var wire 1 C flags_in [1] $end
$var wire 1 D flags_in [0] $end
$var reg 8 E data_out [7:0] $end
$var reg 3 F flags_out [2:0] $end
$var reg 16 G alu_value [15:0] $end
$upscope $end
$upscope $end

$scope begin std $end
$upscope $end
$enddefinitions $end
#0
$dumpvars
0!
1"
x#
x$
x%
bx &
bx '
bz (
bx )
bz E
bx F
bx G
bx *
bx +
bx ,
0-
1.
x/
x0
x1
xA
x@
x?
x>
x=
x<
x;
x:
x9
x8
x7
x6
x5
x4
x3
x2
xD
xC
xB
$end
#50
1!
1-
#100
0!
0-
0"
bz *
b0 +
b110011 ,
0.
#150
1!
1-
b0 G
b0 F
b0 )
#200
0!
0-
1"
b111000 ,
1.
#250
1!
1-
#300
0!
0-
1%
b1111111011101111 &
b101 '
b101 +
b111111 ,
11
1D
0C
1B
1A
1@
1?
1>
0=
1<
1;
1:
09
18
17
16
15
14
13
12
#350
1!
1-
b1111111011101111 G
b101 F
b101 )
#400
0!
0-
0%
b1110111111111110 &
b111 '
b1000110 ,
01
1C
0A
1=
19
05
#450
1!
1-
#500
0!
0-
1#
b11111110 *
b1001011 ,
1/
b11111110 E
b11111110 (
#550
1!
1-
#600
0!
0-
0#
bz *
b1010000 ,
0/
bz E
bz (
#650
1!
1-
#700
0!
0-
1$
b11101111 *
b1010101 ,
10
b11101111 E
b11101111 (
#750
1!
1-
#800
0!
0-
0$
bz *
b1011010 ,
00
bz E
bz (
#850
1!
1-
#900
0!
0-
1#
1$
b11111110 *
b1100000 ,
1/
10
b11111110 E
b11111110 (
