memory_io.sv
//-----------------------------------------------------------------------------
//
// Title       : Memory Input Output
// Author      : vinod sake <vinosake@pdx.edu>
// Company     : Student
//
//-----------------------------------------------------------------------------
//
// File        : memory_io.sv
// Generated   : 14 Dec 2016
// Last Updated: 
//-----------------------------------------------------------------------------
//
// Description : performs mapping between RAM & ROM memory blocks
//		 ROM : 0000 - 1FFF
//		 RAM : 2000 - 3FFF
//-----------------------------------------------------------------------------


module memory_io(
	input read_memory,
	input write_memory,
	input [15:0]address_in,
	inout [7:0]internal_data_bus,
	inout [7:0]external_data_bus,
	output [15:0]address_out,
	output logic ram_enable,		// Active LOW
	output logic rom_enable,		// Active LOW
	output write,
	output read
);
logic [1:0]read_write;
logic enable;

assign read_write = {read_memory,write_memory};
assign enable = read_memory ^ write_memory;

assign internal_data_bus = (read_memory == 1'b1 && enable == 1'b1) ? external_data_bus : 8'hzz;
assign external_data_bus = (write_memory == 1'b1 && enable == 1'b1) ? internal_data_bus : 8'hzz;

always_comb begin
	case(read_write)
		0 : begin
			rom_enable = 1;
			ram_enable = 1; 
		end
		1 : begin
			rom_enable = !(address_in[15:13] === 3'b000);
			ram_enable = !(address_in[15:13] === 3'b001);
		end
		2 : begin
			rom_enable = !(address_in[15:13] === 3'b000);
			ram_enable = !(address_in[15:13] === 3'b001);
		end
		3 : begin			//Invalid
			rom_enable = 1;
			ram_enable = 1;
		end
		default : begin
			rom_enable = 1;
			ram_enable = 1;
		end
	endcase
end	

assign address_out = (address_in > 16'h1fff) ? (address_in - 16'h2000): address_in; 		// Mapping RAM address 
assign write = write_memory;
assign read =  read_memory;

endmodule

memory_io_tb.sv
//-----------------------------------------------------------------------------
//
// Title       : Memory Input Output Testbench
// Author      : vinod sake <vinosake@pdx.edu>
// Company     : Student
//
//-----------------------------------------------------------------------------
//
// File        : memory_io.sv
// Generated   : 18 Dec 2016
// Last Updated: 
//-----------------------------------------------------------------------------
//
// Description : performs testing for mapping between RAM & ROM memory blocks
//		 
//		 	
//-----------------------------------------------------------------------------


module memory_io_tb();
	logic read_memory;
	logic write_memory;
	logic [15:0]address_in;
	logic [15:0]address_out;
	wire [7:0]internal_data_bus;
	wire [7:0]external_data_bus;
	logic ram_enable;
	logic rom_enable;
	logic write;
	logic write_bar;

logic [7:0] internal_data[0:3];
logic [7:0] external_data[0:3];

memory_io memory_io_dut(
	.read_memory(read_memory),
	.write_memory(write_memory),
	.address_in(address_in),
	.address_out(address_out),
	.internal_data_bus(internal_data_bus),
	.external_data_bus(external_data_bus),
	.ram_enable(ram_enable),
	.rom_enable(rom_enable),
	.write(write),
	.read(read)
);

logic internal_control;
logic external_control;
logic [7:0]temp_internal;
logic [7:0]temp_external;

assign internal_data_bus = internal_control ? temp_internal : 8'hzz;
assign external_data_bus = external_control ? temp_external : 8'hzz;
	
logic clock = 1'b0;
always #50 clock = ~clock;

initial begin
	$readmemh("internal_data_bus.txt", internal_data);
	$readmemh("external_data_bus.txt", external_data);
	
	$display("below task is invalid and compiler has to handel this as we cannot perform write operation on ROM");
	@(negedge clock) begin
		address_in = 16'h1ffe;
		read_memory = 0;
		write_memory = 1;
		internal_control = 1;
		temp_external = 0;
		temp_internal = internal_data[0];
	end
	checkwrite(16'h1ffe, 1'b1, 1'b0, 1'b1 , 1'b0 , internal_data[0], `__LINE__);
	
	@(negedge clock) begin
		address_in = 16'h2000;
		read_memory = 0;
		write_memory = 1;
		internal_control = 1;
		temp_internal = internal_data[1];
	end
	checkwrite(16'h2000, 1'b1, 1'b0, 1'b0 , 1'b1 , internal_data[1], `__LINE__);

	@(negedge clock) begin
		address_in = 16'h1fff;
		read_memory = 1;
		write_memory = 0;
		external_control = 1;
		temp_external = external_data[0];
	end
	checkread(16'h1fff, 1'b0, 1'b1, 1'b1, 1'b0, external_data[0], `__LINE__);

	@(negedge clock) begin
		address_in = 16'hffff;
		read_memory = 1;
		write_memory = 0;
		external_control = 1;
		temp_external = external_data[1];
	end
	checkread(16'hffff, 1'b0, 1'b1, 1'b0, 1'b1, external_data[1], `__LINE__);

	@(negedge clock) begin
		address_in = 16'h1fee;
		read_memory = 0;
		write_memory = 0;
		internal_control = 1;
		external_control = 1;
		temp_internal = internal_data[2];	
		temp_external = external_data[2];
	end
	checkwrite(16'h1fee, 1'b0, 1'b0, 1'b1 , 1'b1 , 8'hzz, `__LINE__);
	checkread(16'h1fee, 1'b0, 1'b0, 1'b1 , 1'b1 , 8'hzz, `__LINE__);

	@(negedge clock) begin
		address_in = 16'hffff;
		read_memory = 1;
		write_memory = 1;
		internal_control = 1;
		external_control = 1;
		temp_internal = internal_data[3];	
		temp_external = external_data[3];
	end
	checkwrite(16'h1fee, 1'b1, 1'b1, 1'b1 , 1'b1 , 8'hzz, `__LINE__);
	checkread(16'h1fee, 1'b1, 1'b1, 1'b1 , 1'b1 , 8'hzz, `__LINE__);
	
end

// Waveform log file and monitoring
initial begin
	$dumpfile("register_16bit.vcd");
	$dumpvars();
	//$monitor("time: %d, value: %h", $time, valueout);
end


task checkwrite(input[15:0] address_expected, input write_expected, input read_expected, input ram_enable_expected, input rom_enable_expected, input [7:0]external_data_bus_expected, input integer lineNum);
begin
	@(posedge clock) #5 begin
		if(address_out == address_expected) begin
			$display("%3d - Test passed! for address", lineNum);
		end
		else begin
			$display("%3d - Test failed! for address, expected %h, got %h", lineNum, address_expected, address_out);
		end
		if(ram_enable == ram_enable_expected) begin
			$display("%3d - Test passed! for RAM enable", lineNum);
		end
		else begin
			$display("%3d - Test failed! for RAM enable, expected %d, got %d", lineNum, ram_enable_expected, ram_enable);
		end
		if(rom_enable == rom_enable_expected) begin
			$display("%3d - Test passed! for ROM enable", lineNum);
		end
		else begin
			$display("%3d - Test failed! for ROM enable, expected %d, got %d", lineNum, rom_enable_expected, rom_enable);
		end
		if(write == write_expected) begin
			$display("%3d - Test passed! for write signal", lineNum);
		end
		else begin
			$display("%3d - Test failed! for write signal, expected %d, got %d", lineNum, write_expected, write);
		end
		if(read == read_expected) begin
			$display("%3d - Test passed! for read signal", lineNum);
		end
		else begin
			$display("%3d - Test failed! for read signal, expected %d, got %d", lineNum, read_expected, read);
		end
		if(external_data_bus === external_data_bus_expected) begin
			$display("%3d - Test passed! for data bus", lineNum);
		end
		else begin
			$display("%3d - Test failed! for data bus, expected %d, got %d", lineNum, external_data_bus_expected, external_data_bus);
		end
		
	end
end
endtask

task checkread(input[15:0] address_expected, input write_expected, input ram_enable_expected, input rom_enable_expected, input read_expected, input [7:0]internal_data_bus_expected, input integer lineNum);
begin
	@(posedge clock) #5 begin
		if(address_out == address_expected) begin
			$display("%3d - Test passed! for address", lineNum);
		end
		else begin
			$display("%3d - Test failed! for address, expected %h, got %h", lineNum, address_expected, address_out);
		end
		if(ram_enable == ram_enable_expected) begin
			$display("%3d - Test passed! for RAM enable", lineNum);
		end
		else begin
			$display("%3d - Test failed! for RAM enable, expected %d, got %d", lineNum, ram_enable_expected, ram_enable);
		end
		if(rom_enable == rom_enable_expected) begin
			$display("%3d - Test passed! for ROM enable", lineNum);
		end
		else begin
			$display("%3d - Test failed! for ROM enable, expected %d, got %d", lineNum, rom_enable_expected, rom_enable);
		end
		if(write == write_expected) begin
			$display("%3d - Test passed! for write signal", lineNum);
		end
		else begin
			$display("%3d - Test failed! for write signal, expected %d, got %d", lineNum, write_expected, write);
		end
		if(read == read_expected) begin
			$display("%3d - Test passed! for read signal", lineNum);
		end
		else begin
			$display("%3d - Test failed! for read signal, expected %d, got %d", lineNum, read_expected, read);
		end
		if(internal_data_bus === internal_data_bus_expected) begin
			$display("%3d - Test passed! for data bus", lineNum);
		end
		else begin
			$display("%3d - Test failed! for data bus, expected %d, got %d", lineNum, internal_data_bus_expected, internal_data_bus);
		end
	end
end
endtask

endmodule

register_16bit.vcd
$date
	Fri Dec 23 12:19:48 2016
$end
$version
	ModelSim Version 10.4a
$end
$timescale
	1ns
$end

$scope module memory_io_tb $end
$var reg 1 ! read_memory $end
$var reg 1 " write_memory $end
$var reg 16 # address_in [15:0] $end
$var reg 16 $ address_out [15:0] $end
$var wire 1 % internal_data_bus [7] $end
$var wire 1 & internal_data_bus [6] $end
$var wire 1 ' internal_data_bus [5] $end
$var wire 1 ( internal_data_bus [4] $end
$var wire 1 ) internal_data_bus [3] $end
$var wire 1 * internal_data_bus [2] $end
$var wire 1 + internal_data_bus [1] $end
$var wire 1 , internal_data_bus [0] $end
$var wire 1 - external_data_bus [7] $end
$var wire 1 . external_data_bus [6] $end
$var wire 1 / external_data_bus [5] $end
$var wire 1 0 external_data_bus [4] $end
$var wire 1 1 external_data_bus [3] $end
$var wire 1 2 external_data_bus [2] $end
$var wire 1 3 external_data_bus [1] $end
$var wire 1 4 external_data_bus [0] $end
$var reg 1 5 ram_enable $end
$var reg 1 6 rom_enable $end
$var reg 1 7 write $end
$var reg 1 8 write_bar $end
$var wire 1 9 read $end
$var reg 1 : internal_control $end
$var reg 1 ; external_control $end
$var reg 8 < temp_internal [7:0] $end
$var reg 8 = temp_external [7:0] $end
$var reg 1 > clock $end

$scope task checkwrite $end
$var reg 16 ? address_expected [15:0] $end
$var reg 1 @ write_expected $end
$var reg 1 A read_expected $end
$var reg 1 B ram_enable_expected $end
$var reg 1 C rom_enable_expected $end
$var reg 8 D external_data_bus_expected [7:0] $end
$var integer 32 E lineNum $end
$upscope $end

$scope task checkread $end
$var reg 16 F address_expected [15:0] $end
$var reg 1 G write_expected $end
$var reg 1 H ram_enable_expected $end
$var reg 1 I rom_enable_expected $end
$var reg 1 J read_expected $end
$var reg 8 K internal_data_bus_expected [7:0] $end
$var integer 32 L lineNum $end
$upscope $end

$scope module memory_io_dut $end
$var wire 1 M read_memory $end
$var wire 1 N write_memory $end
$var wire 1 O address_in [15] $end
$var wire 1 P address_in [14] $end
$var wire 1 Q address_in [13] $end
$var wire 1 R address_in [12] $end
$var wire 1 S address_in [11] $end
$var wire 1 T address_in [10] $end
$var wire 1 U address_in [9] $end
$var wire 1 V address_in [8] $end
$var wire 1 W address_in [7] $end
$var wire 1 X address_in [6] $end
$var wire 1 Y address_in [5] $end
$var wire 1 Z address_in [4] $end
$var wire 1 [ address_in [3] $end
$var wire 1 \ address_in [2] $end
$var wire 1 ] address_in [1] $end
$var wire 1 ^ address_in [0] $end
$var wire 1 % internal_data_bus [7] $end
$var wire 1 & internal_data_bus [6] $end
$var wire 1 ' internal_data_bus [5] $end
$var wire 1 ( internal_data_bus [4] $end
$var wire 1 ) internal_data_bus [3] $end
$var wire 1 * internal_data_bus [2] $end
$var wire 1 + internal_data_bus [1] $end
$var wire 1 , internal_data_bus [0] $end
$var wire 1 - external_data_bus [7] $end
$var wire 1 . external_data_bus [6] $end
$var wire 1 / external_data_bus [5] $end
$var wire 1 0 external_data_bus [4] $end
$var wire 1 1 external_data_bus [3] $end
$var wire 1 2 external_data_bus [2] $end
$var wire 1 3 external_data_bus [1] $end
$var wire 1 4 external_data_bus [0] $end
$var wire 1 _ address_out [15] $end
$var wire 1 ` address_out [14] $end
$var wire 1 a address_out [13] $end
$var wire 1 b address_out [12] $end
$var wire 1 c address_out [11] $end
$var wire 1 d address_out [10] $end
$var wire 1 e address_out [9] $end
$var wire 1 f address_out [8] $end
$var wire 1 g address_out [7] $end
$var wire 1 h address_out [6] $end
$var wire 1 i address_out [5] $end
$var wire 1 j address_out [4] $end
$var wire 1 k address_out [3] $end
$var wire 1 l address_out [2] $end
$var wire 1 m address_out [1] $end
$var wire 1 n address_out [0] $end
$var reg 1 o ram_enable $end
$var reg 1 p rom_enable $end
$var wire 1 q write $end
$var wire 1 9 read $end
$var reg 2 r read_write [1:0] $end
$var reg 1 s enable $end
$upscope $end
$upscope $end

$scope begin std $end
$upscope $end
$enddefinitions $end
#0
$dumpvars
x!
x"
bx #
bx $
15
16
x7
x8
1o
1p
bx r
xs
x:
x;
bx <
bx =
0>
bx ?
x@
xA
xB
xC
bx D
bx F
xG
xH
xI
xJ
bx K
bx E
bx L
x,
x+
x*
x)
x(
x'
x&
x%
x4
x3
x2
x1
x0
x/
x.
x-
x9
xM
xN
x^
x]
x\
x[
xZ
xY
xX
xW
xV
xU
xT
xS
xR
xQ
xP
xO
xn
xm
xl
xk
xj
xi
xh
xg
xf
xe
xd
xc
xb
xa
x`
x_
xq
$end
#50
1>
#100
0>
b1111111111110 #
0!
1"
1:
b0 =
b10101010 <
b1111111111110 ?
1@
0A
1B
0C
b10101010 D
b1001000 E
0M
1N
b1 r
1s
09
0,
1+
0*
1)
0(
1'
0&
1%
1q
17
0^
1]
1\
1[
1Z
1Y
1X
1W
1V
1U
1T
1S
1R
0Q
0P
0O
0n
1m
1l
1k
1j
1i
1h
1g
1f
1e
1d
1c
1b
0a
0`
0_
b1111111111110 $
0p
06
#150
1>
#200
0>
b10000000000000 #
b10111011 <
b10000000000000 ?
0B
1C
b10111011 D
b1010001 E
1,
1(
0]
0\
0[
0Z
0Y
0X
0W
0V
0U
0T
0S
0R
1Q
0m
0l
0k
0j
0i
0h
0g
0f
0e
0d
0c
0b
1a
b10000000000000 $
1p
0o
05
16
#250
1>
#300
0>
b1111111111111 #
1!
0"
1;
b11111111 =
b1111111111111 F
0G
1H
1I
0J
b11111111 K
b1011010 L
1M
0N
14
13
11
10
1/
1-
b10 r
19
0q
12
1.
x*
x&
07
1^
1]
1\
1[
1Z
1Y
1X
1W
1V
1U
1T
1S
1R
0Q
1n
1m
1l
1k
1j
1i
1h
1g
1f
1e
1d
1c
1b
0a
b1111111111111 $
1o
15
#350
1>
#400
0>
b1111111111111111 #
b11101110 =
b1111111111111111 F
0I
1J
b11101110 K
b1100011 L
04
00
x,
x(
1Q
1P
1O
1a
1`
1_
b1111111111111111 $
#450
1>
#500
0>
b1111111101110 #
0!
b11001100 <
b11011101 =
b1111111101110 ?
0@
1B
bz D
b1101110 E
0M
14
03
10
0/
0,
x+
1*
0(
x'
1&
b0 r
0s
09
0+
0'
0^
0Z
0Q
0P
0O
0n
0j
0a
0`
0_
b1111111101110 $
#550
1>
#555
b1111111101110 F
0H
1I
bz K
b1101111 L
#600
0>
#650
1>
#700
0>
b1111111111111111 #
1!
1"
b11011101 <
b11001100 =
1@
1A
b1111010 E
1M
1N
04
00
1,
1(
b11 r
19
1q
17
1^
1Z
1Q
1P
1O
1n
1j
1a
1`
1_
b1111111111111111 $
#750
1>
#755
1G
1H
b1111011 L
